storage_remote_graphql/__init__.py
storage_remote_graphql/remote_storage.py
storage_remote_graphql-0.0.16.dist-info/METADATA
storage_remote_graphql-0.0.16.dist-info/WHEEL
storage_remote_graphql-0.0.16.dist-info/top_level.txt
storage_remote_graphql-0.0.16.dist-info/RECORD
