Metadata-Version: 2.4
Name: storage-remote-graphql
Version: 0.0.16
Home-page: https://github.com/circles-zone/storage-remote-graphql-python-package
Author: Circles
Author-email: info@circlez.ai
Classifier: Programming Language :: Python :: 3
Classifier: Operating System :: OS Independent
Requires-Dist: requests>=2.32.4
Requires-Dist: python-sdk-remote>=0.0.93
Requires-Dist: url-remote>=0.0.28
Dynamic: author
Dynamic: author-email
Dynamic: classifier
Dynamic: description
Dynamic: description-content-type
Dynamic: home-page
Dynamic: requires-dist
